{
  "container": "atg-bucket-update-record",
  "key": "schema",
  "value": {
    "description": "Schema for ATG bucketUpdateRecord custom object",
    "fields": {
      "bucketType": {
        "description": "Property stored in Custom Object 'bucket-update-record'",
        "type": "custom_object_field"
      },
      "date_stamp": {
        "description": "Property stored in Custom Object 'bucket-update-record'",
        "type": "custom_object_field"
      },
      "netChange": {
        "description": "Property stored in Custom Object 'bucket-update-record'",
        "type": "custom_object_field"
      },
      "subscriptionId": {
        "description": "Property stored in Custom Object 'bucket-update-record'",
        "type": "custom_object_field"
      },
      "userId": {
        "description": "Property stored in Custom Object 'bucket-update-record'",
        "type": "custom_object_field"
      }
    },
    "name": "Bucket Update Record"
  }
}
